{
  "$schema": "http://json-schema.org/draft-07/schema#",
  "title": "Flutter Debug Configuration",
  "description": "Configuration for debugging Flutter applications and tests using the official Flutter SDK debug adapter",
  "type": "object",
  "properties": {
    "adapter": {
      "type": "string",
      "enum": ["Flutter"],
      "description": "Debug adapter identifier"
    },
    "label": {
      "type": "string",
      "description": "Human-readable label for this debug configuration"
    },
    "request": {
      "type": "string",
      "enum": ["launch", "attach"],
      "description": "Whether to launch a new process or attach to an existing one"
    },
    "program": {
      "type": "string",
      "description": "Path to the Dart entrypoint file (relative to cwd)",
      "default": "lib/main.dart"
    },
    "cwd": {
      "type": "string",
      "description": "Working directory for the debug session",
      "default": "$ZED_WORKTREE_ROOT"
    },
    "args": {
      "type": "array",
      "items": { "type": "string" },
      "description": "Additional arguments passed to Flutter run",
      "default": []
    },
    "env": {
      "type": "object",
      "additionalProperties": { "type": "string" },
      "description": "Environment variables for the debug session",
      "default": {}
    },
    "vmServiceUri": {
      "type": "string",
      "description": "VM service URI for attach mode"
    },
    "testMode": {
      "type": "boolean",
      "description": "Run using the test debug adapter (flutter debug-adapter --test)",
      "default": false
    },
    "flutterSdkPath": {
      "type": "string",
      "description": "Optional explicit path to the Flutter SDK binary"
    },
    "stopOnEntry": {
      "type": "boolean",
      "description": "Pause execution at the program entry point",
      "default": false
    }
  },
  "required": ["adapter", "label", "request"],
  "oneOf": [
    {
      "properties": {
        "request": { "const": "launch" }
      },
      "required": ["program"]
    },
    {
      "properties": {
        "request": { "const": "attach" }
      },
      "required": ["vmServiceUri"]
    }
  ]
}
